<annotation>
	<folder>CVC-ColonJPGs</folder>
	<filename>206.jpg</filename>
	<path>/Users/iamjacobi/Downloads/CVC-ColonDB/CVC-ColonJPGs/206.jpg</path>
	<source>
		<database>Unknown</database>
	</source>
	<size>
		<width>574</width>
		<height>500</height>
		<depth>3</depth>
	</size>
	<segmented>0</segmented>
	<object>
		<name>polyp</name>
		<pose>Unspecified</pose>
		<truncated>0</truncated>
		<difficult>0</difficult>
		<bndbox>
			<xmin>286</xmin>
			<ymin>229</ymin>
			<xmax>384</xmax>
			<ymax>275</ymax>
		</bndbox>
	</object>
</annotation>
