<annotation>
	<folder>CVC-ColonJPGs</folder>
	<filename>66.jpg</filename>
	<path>/Users/iamjacobi/Downloads/CVC-ColonDB/CVC-ColonJPGs/66.jpg</path>
	<source>
		<database>Unknown</database>
	</source>
	<size>
		<width>574</width>
		<height>500</height>
		<depth>3</depth>
	</size>
	<segmented>0</segmented>
	<object>
		<name>polyp</name>
		<pose>Unspecified</pose>
		<truncated>0</truncated>
		<difficult>0</difficult>
		<bndbox>
			<xmin>282</xmin>
			<ymin>204</ymin>
			<xmax>432</xmax>
			<ymax>434</ymax>
		</bndbox>
	</object>
	<object>
		<name>polyp</name>
		<pose>Unspecified</pose>
		<truncated>0</truncated>
		<difficult>0</difficult>
		<bndbox>
			<xmin>17</xmin>
			<ymin>373</ymin>
			<xmax>103</xmax>
			<ymax>424</ymax>
		</bndbox>
	</object>
	<object>
		<name>polyp</name>
		<pose>Unspecified</pose>
		<truncated>0</truncated>
		<difficult>0</difficult>
		<bndbox>
			<xmin>287</xmin>
			<ymin>122</ymin>
			<xmax>318</xmax>
			<ymax>149</ymax>
		</bndbox>
	</object>
	<object>
		<name>polyp</name>
		<pose>Unspecified</pose>
		<truncated>0</truncated>
		<difficult>0</difficult>
		<bndbox>
			<xmin>299</xmin>
			<ymin>77</ymin>
			<xmax>326</xmax>
			<ymax>101</ymax>
		</bndbox>
	</object>
	<object>
		<name>polyp</name>
		<pose>Unspecified</pose>
		<truncated>0</truncated>
		<difficult>0</difficult>
		<bndbox>
			<xmin>238</xmin>
			<ymin>261</ymin>
			<xmax>269</xmax>
			<ymax>288</ymax>
		</bndbox>
	</object>
</annotation>
